qiniufs.py
setup.cfg
setup.py
qiniufs.egg-info/PKG-INFO
qiniufs.egg-info/SOURCES.txt
qiniufs.egg-info/dependency_links.txt
qiniufs.egg-info/requires.txt
qiniufs.egg-info/top_level.txt